{
"meta":{"test_sets":[],"test_metrics":[],"learn_metrics":[{"best_value":"Min","name":"Logloss"}],"launch_mode":"Train","parameters":"","iteration_count":500,"learn_sets":["learn"],"name":"experiment"},
"iterations":[
{"learn":[0.6930065446],"iteration":0,"passed_time":0.1692212916,"remaining_time":84.4414245},
{"learn":[0.692828208],"iteration":1,"passed_time":0.1976308433,"remaining_time":49.21007998},
{"learn":[0.6926453778],"iteration":2,"passed_time":0.2075842571,"remaining_time":34.38979192},
{"learn":[0.6924683987],"iteration":3,"passed_time":0.2238809832,"remaining_time":27.76124192},
{"learn":[0.6923178098],"iteration":4,"passed_time":0.2359915258,"remaining_time":23.36316105},
{"learn":[0.6921825947],"iteration":5,"passed_time":0.2495315181,"remaining_time":20.54476166},
{"learn":[0.6920551756],"iteration":6,"passed_time":0.2633591955,"remaining_time":18.54801191},
{"learn":[0.6919209733],"iteration":7,"passed_time":0.2726703165,"remaining_time":16.76922447},
{"learn":[0.6917472404],"iteration":8,"passed_time":0.2918908332,"remaining_time":15.92426657},
{"learn":[0.6915934948],"iteration":9,"passed_time":0.3055231724,"remaining_time":14.97063545},
{"learn":[0.6914172517],"iteration":10,"passed_time":0.3193622239,"remaining_time":14.1971025},
{"learn":[0.6913036951],"iteration":11,"passed_time":0.3344668348,"remaining_time":13.60165128},
{"learn":[0.6912022815],"iteration":12,"passed_time":0.3494169924,"remaining_time":13.0896981},
{"learn":[0.6910919277],"iteration":13,"passed_time":0.3633003062,"remaining_time":12.61171063},
{"learn":[0.6909861157],"iteration":14,"passed_time":0.3721117497,"remaining_time":12.03161324},
{"learn":[0.6908735339],"iteration":15,"passed_time":0.3832982403,"remaining_time":11.59477177},
{"learn":[0.6907367911],"iteration":16,"passed_time":0.3937655918,"remaining_time":11.18757534},
{"learn":[0.6906315191],"iteration":17,"passed_time":0.4013521919,"remaining_time":10.7473198},
{"learn":[0.6905118398],"iteration":18,"passed_time":0.418074684,"remaining_time":10.58389068},
{"learn":[0.6904427727],"iteration":19,"passed_time":0.428367052,"remaining_time":10.28080925},
{"learn":[0.6903886368],"iteration":20,"passed_time":0.4348482396,"remaining_time":9.918681274},
{"learn":[0.6902524374],"iteration":21,"passed_time":0.4463720096,"remaining_time":9.698446391},
{"learn":[0.6901294744],"iteration":22,"passed_time":0.4549882743,"remaining_time":9.436061168},
{"learn":[0.6899716162],"iteration":23,"passed_time":0.4665402313,"remaining_time":9.25304792},
{"learn":[0.6898595215],"iteration":24,"passed_time":0.478922054,"remaining_time":9.099519026},
{"learn":[0.6897632775],"iteration":25,"passed_time":0.4872316525,"remaining_time":8.88260782},
{"learn":[0.6896525211],"iteration":26,"passed_time":0.4983414163,"remaining_time":8.730203331},
{"learn":[0.6895874718],"iteration":27,"passed_time":0.5050615826,"remaining_time":8.513895249},
{"learn":[0.6894813003],"iteration":28,"passed_time":0.5154696772,"remaining_time":8.37193855},
{"learn":[0.6893776904],"iteration":29,"passed_time":0.5260833033,"remaining_time":8.241971752},
{"learn":[0.6892690546],"iteration":30,"passed_time":0.5342156749,"remaining_time":8.082166178},
{"learn":[0.6891732486],"iteration":31,"passed_time":0.5445884423,"remaining_time":7.964605969},
{"learn":[0.689085893],"iteration":32,"passed_time":0.5527631604,"remaining_time":7.822436239},
{"learn":[0.6890408918],"iteration":33,"passed_time":0.5636970406,"remaining_time":7.725965322},
{"learn":[0.6889485093],"iteration":34,"passed_time":0.5739168268,"remaining_time":7.624894985},
{"learn":[0.688859276],"iteration":35,"passed_time":0.582373259,"remaining_time":7.506144227},
{"learn":[0.6887566203],"iteration":36,"passed_time":0.5901147879,"remaining_time":7.384409373},
{"learn":[0.6886644863],"iteration":37,"passed_time":0.5964675109,"remaining_time":7.251789211},
{"learn":[0.688558119],"iteration":38,"passed_time":0.6025562223,"remaining_time":7.122523551},
{"learn":[0.6884787974],"iteration":39,"passed_time":0.6085699489,"remaining_time":6.998554412},
{"learn":[0.6883697648],"iteration":40,"passed_time":0.6149110692,"remaining_time":6.884004409},
{"learn":[0.6882478011],"iteration":41,"passed_time":0.6219188182,"remaining_time":6.781876637},
{"learn":[0.688153255],"iteration":42,"passed_time":0.6280284791,"remaining_time":6.674628254},
{"learn":[0.6880830786],"iteration":43,"passed_time":0.6339733124,"remaining_time":6.570268874},
{"learn":[0.6880267738],"iteration":44,"passed_time":0.6400413046,"remaining_time":6.471528746},
{"learn":[0.6879355406],"iteration":45,"passed_time":0.646222586,"remaining_time":6.377935958},
{"learn":[0.6878275199],"iteration":46,"passed_time":0.6524807711,"remaining_time":6.288804028},
{"learn":[0.6877476175],"iteration":47,"passed_time":0.6597371943,"remaining_time":6.212525247},
{"learn":[0.6876499271],"iteration":48,"passed_time":0.6660044675,"remaining_time":6.129959487},
{"learn":[0.687579671],"iteration":49,"passed_time":0.6761502482,"remaining_time":6.085352233},
{"learn":[0.687478567],"iteration":50,"passed_time":0.6836225834,"remaining_time":6.018559607},
{"learn":[0.6873617748],"iteration":51,"passed_time":0.6909041227,"remaining_time":5.95240475},
{"learn":[0.6873149098],"iteration":52,"passed_time":0.695873965,"remaining_time":5.868974761},
{"learn":[0.6872348338],"iteration":53,"passed_time":0.7025049834,"remaining_time":5.802170789},
{"learn":[0.6871644679],"iteration":54,"passed_time":0.7089755329,"remaining_time":5.736256585},
{"learn":[0.6871175919],"iteration":55,"passed_time":0.7136427591,"remaining_time":5.65816759},
{"learn":[0.6870423894],"iteration":56,"passed_time":0.7189666223,"remaining_time":5.587758135},
{"learn":[0.6869756276],"iteration":57,"passed_time":0.7251333315,"remaining_time":5.526016078},
{"learn":[0.6868693741],"iteration":58,"passed_time":0.73122234,"remaining_time":5.465577151},
{"learn":[0.6867927493],"iteration":59,"passed_time":0.738056019,"remaining_time":5.412410806},
{"learn":[0.6867242243],"iteration":60,"passed_time":0.7440919205,"remaining_time":5.355022182},
{"learn":[0.6866845821],"iteration":61,"passed_time":0.7489577488,"remaining_time":5.291024096},
{"learn":[0.6866245924],"iteration":62,"passed_time":0.7722186288,"remaining_time":5.356500648},
{"learn":[0.6865588377],"iteration":63,"passed_time":0.778653815,"remaining_time":5.304579115},
{"learn":[0.6864913501],"iteration":64,"passed_time":0.7840830511,"remaining_time":5.247325034},
{"learn":[0.6864225129],"iteration":65,"passed_time":0.7907390474,"remaining_time":5.199708281},
{"learn":[0.6863426164],"iteration":66,"passed_time":0.7976775583,"remaining_time":5.155140041},
{"learn":[0.6862756089],"iteration":67,"passed_time":0.8042542173,"remaining_time":5.109379733},
{"learn":[0.6861970091],"iteration":68,"passed_time":0.8091250639,"remaining_time":5.054100037},
{"learn":[0.6861286806],"iteration":69,"passed_time":0.8167317069,"remaining_time":5.0170662},
{"learn":[0.6860461847],"iteration":70,"passed_time":0.8800674126,"remaining_time":5.317590423},
{"learn":[0.6859746705],"iteration":71,"passed_time":0.9123290447,"remaining_time":5.423289321},
{"learn":[0.6859442695],"iteration":72,"passed_time":0.9259171349,"remaining_time":5.415981049},
{"learn":[0.6858854104],"iteration":73,"passed_time":0.9546387975,"remaining_time":5.495623348},
{"learn":[0.6858266612],"iteration":74,"passed_time":0.9665574258,"remaining_time":5.477158746},
{"learn":[0.6857419462],"iteration":75,"passed_time":0.9797839194,"remaining_time":5.466162919},
{"learn":[0.6856690424],"iteration":76,"passed_time":0.9972827161,"remaining_time":5.478579077},
{"learn":[0.6856098439],"iteration":77,"passed_time":1.020769136,"remaining_time":5.522622761},
{"learn":[0.6855513157],"iteration":78,"passed_time":1.041683592,"remaining_time":5.551250537},
{"learn":[0.6855037353],"iteration":79,"passed_time":1.055185278,"remaining_time":5.539722708},
{"learn":[0.6854263998],"iteration":80,"passed_time":1.073440994,"remaining_time":5.552737981},
{"learn":[0.6853762471],"iteration":81,"passed_time":1.079276742,"remaining_time":5.501679001},
{"learn":[0.6852887751],"iteration":82,"passed_time":1.08741371,"remaining_time":5.463271289},
{"learn":[0.6852241943],"iteration":83,"passed_time":1.094335222,"remaining_time":5.419564908},
{"learn":[0.6851267529],"iteration":84,"passed_time":1.103752555,"remaining_time":5.388909533},
{"learn":[0.6850802326],"iteration":85,"passed_time":1.108758877,"remaining_time":5.337513664},
{"learn":[0.6849900229],"iteration":86,"passed_time":1.114061399,"remaining_time":5.288590319},
{"learn":[0.6849283599],"iteration":87,"passed_time":1.12135017,"remaining_time":5.249957615},
{"learn":[0.6848663849],"iteration":88,"passed_time":1.126701066,"remaining_time":5.203080205},
{"learn":[0.6848170818],"iteration":89,"passed_time":1.133363345,"remaining_time":5.163099685},
{"learn":[0.6847363605],"iteration":90,"passed_time":1.140091841,"remaining_time":5.124149042},
{"learn":[0.6846772728],"iteration":91,"passed_time":1.14551519,"remaining_time":5.080110842},
{"learn":[0.6846251274],"iteration":92,"passed_time":1.154126026,"remaining_time":5.050852609},
{"learn":[0.6845374787],"iteration":93,"passed_time":1.15977393,"remaining_time":5.009236336},
{"learn":[0.6844880941],"iteration":94,"passed_time":1.16485934,"remaining_time":4.965979291},
{"learn":[0.6844258715],"iteration":95,"passed_time":1.177393947,"remaining_time":4.954866192},
{"learn":[0.6843678036],"iteration":96,"passed_time":1.189984662,"remaining_time":4.943956894},
{"learn":[0.6843101605],"iteration":97,"passed_time":1.196371725,"remaining_time":4.907565649},
{"learn":[0.6842305522],"iteration":98,"passed_time":1.203743639,"remaining_time":4.87576969},
{"learn":[0.6841756251],"iteration":99,"passed_time":1.209528158,"remaining_time":4.838112633},
{"learn":[0.6841098051],"iteration":100,"passed_time":1.216832643,"remaining_time":4.807091333},
{"learn":[0.6840416311],"iteration":101,"passed_time":1.222666633,"remaining_time":4.770797256},
{"learn":[0.6839754975],"iteration":102,"passed_time":1.227974361,"remaining_time":4.733066227},
{"learn":[0.6839282787],"iteration":103,"passed_time":1.235649946,"remaining_time":4.704974795},
{"learn":[0.6838770938],"iteration":104,"passed_time":1.24113665,"remaining_time":4.669037874},
{"learn":[0.683819992],"iteration":105,"passed_time":1.249765847,"remaining_time":4.645356072},
{"learn":[0.683747423],"iteration":106,"passed_time":1.257066226,"remaining_time":4.617075016},
{"learn":[0.6836879347],"iteration":107,"passed_time":1.262552076,"remaining_time":4.582596424},
{"learn":[0.6836153801],"iteration":108,"passed_time":1.269445389,"remaining_time":4.553698598},
{"learn":[0.683566146],"iteration":109,"passed_time":1.274915842,"remaining_time":4.520156169},
{"learn":[0.6835148553],"iteration":110,"passed_time":1.282487916,"remaining_time":4.494484678},
{"learn":[0.6834612028],"iteration":111,"passed_time":1.287663542,"remaining_time":4.460834415},
{"learn":[0.6834001856],"iteration":112,"passed_time":1.293184629,"remaining_time":4.42887125},
{"learn":[0.683343583],"iteration":113,"passed_time":1.300421755,"remaining_time":4.403182432},
{"learn":[0.6833076081],"iteration":114,"passed_time":1.30483784,"remaining_time":4.368370159},
{"learn":[0.6832462093],"iteration":115,"passed_time":1.31042747,"remaining_time":4.337966798},
{"learn":[0.6831709843],"iteration":116,"passed_time":1.317768519,"remaining_time":4.31372088},
{"learn":[0.6831099946],"iteration":117,"passed_time":1.323118764,"remaining_time":4.283316677},
{"learn":[0.6830708803],"iteration":118,"passed_time":1.330536046,"remaining_time":4.259951543},
{"learn":[0.6830228009],"iteration":119,"passed_time":1.335733774,"remaining_time":4.229823616},
{"learn":[0.6829641809],"iteration":120,"passed_time":1.341132566,"remaining_time":4.200737541},
{"learn":[0.6829194501],"iteration":121,"passed_time":1.34825419,"remaining_time":4.177377737},
{"learn":[0.6828593844],"iteration":122,"passed_time":1.353577539,"remaining_time":4.148770181},
{"learn":[0.68281599],"iteration":123,"passed_time":1.358618146,"remaining_time":4.11968083},
{"learn":[0.682784351],"iteration":124,"passed_time":1.365522629,"remaining_time":4.096567886},
{"learn":[0.6827385358],"iteration":125,"passed_time":1.370967534,"remaining_time":4.069379822},
{"learn":[0.682687615],"iteration":126,"passed_time":1.376571864,"remaining_time":4.043002404},
{"learn":[0.6826398447],"iteration":127,"passed_time":1.384518345,"remaining_time":4.02375644},
{"learn":[0.6825793684],"iteration":128,"passed_time":1.389833558,"remaining_time":3.997118216},
{"learn":[0.6825342414],"iteration":129,"passed_time":1.397212858,"remaining_time":3.97668275},
{"learn":[0.6824887579],"iteration":130,"passed_time":1.402675752,"remaining_time":3.951048493},
{"learn":[0.682428098],"iteration":131,"passed_time":1.408031003,"remaining_time":3.925419767},
{"learn":[0.6823675759],"iteration":132,"passed_time":1.415041878,"remaining_time":3.904664431},
{"learn":[0.6823145837],"iteration":133,"passed_time":1.420419948,"remaining_time":3.879654485},
{"learn":[0.6822438906],"iteration":134,"passed_time":1.426018661,"remaining_time":3.855531936},
{"learn":[0.6822013896],"iteration":135,"passed_time":1.432665411,"remaining_time":3.834486836},
{"learn":[0.6821562066],"iteration":136,"passed_time":1.438154391,"remaining_time":3.810584261},
{"learn":[0.6821151237],"iteration":137,"passed_time":1.44480391,"remaining_time":3.789992865},
{"learn":[0.6820456507],"iteration":138,"passed_time":1.451946683,"remaining_time":3.770883112},
{"learn":[0.6820064008],"iteration":139,"passed_time":1.460939193,"remaining_time":3.756700781},
{"learn":[0.681959195],"iteration":140,"passed_time":1.469554226,"remaining_time":3.741630972},
{"learn":[0.6819186923],"iteration":141,"passed_time":1.479809889,"remaining_time":3.730788313},
{"learn":[0.6818726982],"iteration":142,"passed_time":1.488305839,"remaining_time":3.71556073},
{"learn":[0.6818244961],"iteration":143,"passed_time":1.495664215,"remaining_time":3.697614308},
{"learn":[0.6817599533],"iteration":144,"passed_time":1.501918444,"remaining_time":3.677110673},
{"learn":[0.6817094595],"iteration":145,"passed_time":1.513394274,"remaining_time":3.66946283},
{"learn":[0.6816375633],"iteration":146,"passed_time":1.523912356,"remaining_time":3.659463004},
{"learn":[0.6816022488],"iteration":147,"passed_time":1.539083528,"remaining_time":3.660522986},
{"learn":[0.6815746659],"iteration":148,"passed_time":1.548954222,"remaining_time":3.648878738},
{"learn":[0.6815264346],"iteration":149,"passed_time":1.555444325,"remaining_time":3.629370092},
{"learn":[0.6814734515],"iteration":150,"passed_time":1.562589547,"remaining_time":3.611548026},
{"learn":[0.6814229681],"iteration":151,"passed_time":1.568256174,"remaining_time":3.59048124},
{"learn":[0.6813878307],"iteration":152,"passed_time":1.573795708,"remaining_time":3.569327522},
{"learn":[0.6813386307],"iteration":153,"passed_time":1.58095853,"remaining_time":3.55202371},
{"learn":[0.6812741018],"iteration":154,"passed_time":1.587202436,"remaining_time":3.532805421},
{"learn":[0.6812185184],"iteration":155,"passed_time":1.594764074,"remaining_time":3.516659241},
{"learn":[0.6811759672],"iteration":156,"passed_time":1.600772513,"remaining_time":3.497229121},
{"learn":[0.6811241312],"iteration":157,"passed_time":1.606517777,"remaining_time":3.477399239},
{"learn":[0.6810752154],"iteration":158,"passed_time":1.612832826,"remaining_time":3.458968513},
{"learn":[0.6810336026],"iteration":159,"passed_time":1.618336288,"remaining_time":3.438964611},
{"learn":[0.6809940904],"iteration":160,"passed_time":1.62481301,"remaining_time":3.421190127},
{"learn":[0.6809472011],"iteration":161,"passed_time":1.630181592,"remaining_time":3.401243075},
{"learn":[0.6809098339],"iteration":162,"passed_time":1.635784943,"remaining_time":3.381960281},
{"learn":[0.680873462],"iteration":163,"passed_time":1.641766427,"remaining_time":3.363619022},
{"learn":[0.6807851819],"iteration":164,"passed_time":1.647022125,"remaining_time":3.343954011},
{"learn":[0.6807495666],"iteration":165,"passed_time":1.652330333,"remaining_time":3.324568259},
{"learn":[0.6807010331],"iteration":166,"passed_time":1.66250254,"remaining_time":3.315049975},
{"learn":[0.6806495677],"iteration":167,"passed_time":1.669090169,"remaining_time":3.298440096},
{"learn":[0.6806066359],"iteration":168,"passed_time":1.675366474,"remaining_time":3.28133907},
{"learn":[0.6805598639],"iteration":169,"passed_time":1.680705298,"remaining_time":3.262545578},
{"learn":[0.6805101197],"iteration":170,"passed_time":1.686470749,"remaining_time":3.244730271},
{"learn":[0.6804385106],"iteration":171,"passed_time":1.692954091,"remaining_time":3.228424081},
{"learn":[0.6803948987],"iteration":172,"passed_time":1.698188806,"remaining_time":3.209871327},
{"learn":[0.6803519014],"iteration":173,"passed_time":1.703756048,"remaining_time":3.192094665},
{"learn":[0.6803163944],"iteration":174,"passed_time":1.710972752,"remaining_time":3.177520825},
{"learn":[0.6802538826],"iteration":175,"passed_time":1.716135514,"remaining_time":3.159249469},
{"learn":[0.6802032437],"iteration":176,"passed_time":1.721858983,"remaining_time":3.142149443},
{"learn":[0.6801777459],"iteration":177,"passed_time":1.727770657,"remaining_time":3.125517705},
{"learn":[0.6801619461],"iteration":178,"passed_time":1.732068397,"remaining_time":3.106111482},
{"learn":[0.6801041432],"iteration":179,"passed_time":1.737366273,"remaining_time":3.088651152},
{"learn":[0.6800756728],"iteration":180,"passed_time":1.744532433,"remaining_time":3.074617934},
{"learn":[0.6800299412],"iteration":181,"passed_time":1.750507225,"remaining_time":3.058578557},
{"learn":[0.6800001582],"iteration":182,"passed_time":1.756225546,"remaining_time":3.042204908},
{"learn":[0.6799612417],"iteration":183,"passed_time":1.761479264,"remaining_time":3.02514917},
{"learn":[0.6799063178],"iteration":184,"passed_time":1.76690606,"remaining_time":3.008515723},
{"learn":[0.6798646257],"iteration":185,"passed_time":1.774484452,"remaining_time":2.995635042},
{"learn":[0.679850531],"iteration":186,"passed_time":1.779568864,"remaining_time":2.978636654},
{"learn":[0.6798059123],"iteration":187,"passed_time":1.785010308,"remaining_time":2.962357532},
{"learn":[0.6797336155],"iteration":188,"passed_time":1.791204977,"remaining_time":2.947432529},
{"learn":[0.6797043229],"iteration":189,"passed_time":1.796651597,"remaining_time":2.931378921},
{"learn":[0.679659029],"iteration":190,"passed_time":1.802304395,"remaining_time":2.915769937},
{"learn":[0.6796201666],"iteration":191,"passed_time":1.809257388,"remaining_time":2.902350393},
{"learn":[0.6795550395],"iteration":192,"passed_time":1.814494064,"remaining_time":2.886267759},
{"learn":[0.6795031521],"iteration":193,"passed_time":1.820523061,"remaining_time":2.871546683},
{"learn":[0.6794721157],"iteration":194,"passed_time":1.827693727,"remaining_time":2.858700445},
{"learn":[0.6794314263],"iteration":195,"passed_time":1.833075606,"remaining_time":2.843137675},
{"learn":[0.6794072464],"iteration":196,"passed_time":1.839740582,"remaining_time":2.829651759},
{"learn":[0.6793612918],"iteration":197,"passed_time":1.845874047,"remaining_time":2.815424052},
{"learn":[0.6793163948],"iteration":198,"passed_time":1.850925752,"remaining_time":2.799641465},
{"learn":[0.6792699662],"iteration":199,"passed_time":1.861437016,"remaining_time":2.792155524},
{"learn":[0.6792177538],"iteration":200,"passed_time":1.872112664,"remaining_time":2.784884012},
{"learn":[0.6791758832],"iteration":201,"passed_time":1.879900027,"remaining_time":2.773317862},
{"learn":[0.6791282121],"iteration":202,"passed_time":1.888101893,"remaining_time":2.762395381},
{"learn":[0.6790886972],"iteration":203,"passed_time":1.89358447,"remaining_time":2.747553937},
{"learn":[0.6790463552],"iteration":204,"passed_time":1.898998395,"remaining_time":2.732705007},
{"learn":[0.6790103427],"iteration":205,"passed_time":1.905795428,"remaining_time":2.71992163},
{"learn":[0.6789728712],"iteration":206,"passed_time":1.911221953,"remaining_time":2.705256194},
{"learn":[0.6789596067],"iteration":207,"passed_time":1.915934317,"remaining_time":2.689677022},
{"learn":[0.6789444634],"iteration":208,"passed_time":1.921404556,"remaining_time":2.675257062},
{"learn":[0.6789075318],"iteration":209,"passed_time":1.926973737,"remaining_time":2.66105897},
{"learn":[0.6788705836],"iteration":210,"passed_time":1.932321722,"remaining_time":2.646639705},
{"learn":[0.6788369694],"iteration":211,"passed_time":1.938115977,"remaining_time":2.632912271},
{"learn":[0.6787986524],"iteration":212,"passed_time":1.943614812,"remaining_time":2.618861273},
{"learn":[0.6787597508],"iteration":213,"passed_time":1.949077756,"remaining_time":2.604842234},
{"learn":[0.6787098886],"iteration":214,"passed_time":1.955310071,"remaining_time":2.591922653},
{"learn":[0.6786758915],"iteration":215,"passed_time":1.960796542,"remaining_time":2.578084343},
{"learn":[0.6786598884],"iteration":216,"passed_time":1.96537709,"remaining_time":2.563141551},
{"learn":[0.6786261353],"iteration":217,"passed_time":1.971404778,"remaining_time":2.550165813},
{"learn":[0.6785839166],"iteration":218,"passed_time":1.976574433,"remaining_time":2.536152583},
{"learn":[0.6785402816],"iteration":219,"passed_time":1.981921842,"remaining_time":2.522445981},
{"learn":[0.6784907719],"iteration":220,"passed_time":1.988249376,"remaining_time":2.51005238},
{"learn":[0.6784475606],"iteration":221,"passed_time":1.993610737,"remaining_time":2.496503535},
{"learn":[0.6784117487],"iteration":222,"passed_time":1.998928311,"remaining_time":2.482973731},
{"learn":[0.6783615463],"iteration":223,"passed_time":2.00488583,"remaining_time":2.470305755},
{"learn":[0.6783179293],"iteration":224,"passed_time":2.010329934,"remaining_time":2.45706992},
{"learn":[0.6782866033],"iteration":225,"passed_time":2.016314554,"remaining_time":2.444558353},
{"learn":[0.6782335476],"iteration":226,"passed_time":2.022125414,"remaining_time":2.431895322},
{"learn":[0.6782103017],"iteration":227,"passed_time":2.027678737,"remaining_time":2.41898516},
{"learn":[0.6781725576],"iteration":228,"passed_time":2.033695729,"remaining_time":2.406687959},
{"learn":[0.6781230819],"iteration":229,"passed_time":2.038993577,"remaining_time":2.393601155},
{"learn":[0.6780961974],"iteration":230,"passed_time":2.044471676,"remaining_time":2.380791692},
{"learn":[0.6780544667],"iteration":231,"passed_time":2.05068452,"remaining_time":2.368894187},
{"learn":[0.678014104],"iteration":232,"passed_time":2.056004793,"remaining_time":2.35602266},
{"learn":[0.6779719036],"iteration":233,"passed_time":2.061218657,"remaining_time":2.343094712},
{"learn":[0.6779410883],"iteration":234,"passed_time":2.068820324,"remaining_time":2.332925046},
{"learn":[0.6779390488],"iteration":235,"passed_time":2.072277446,"remaining_time":2.318140872},
{"learn":[0.6779140132],"iteration":236,"passed_time":2.077394725,"remaining_time":2.305294568},
{"learn":[0.6778824252],"iteration":237,"passed_time":2.083273713,"remaining_time":2.293351734},
{"learn":[0.6778505856],"iteration":238,"passed_time":2.088594403,"remaining_time":2.280849954},
{"learn":[0.6778099522],"iteration":239,"passed_time":2.094151166,"remaining_time":2.268663763},
{"learn":[0.677743361],"iteration":240,"passed_time":2.100911978,"remaining_time":2.257826565},
{"learn":[0.67771567],"iteration":241,"passed_time":2.106446125,"remaining_time":2.24571529},
{"learn":[0.6776841269],"iteration":242,"passed_time":2.112127237,"remaining_time":2.23381358},
{"learn":[0.6776504695],"iteration":243,"passed_time":2.1180714,"remaining_time":2.222238846},
{"learn":[0.6776041819],"iteration":244,"passed_time":2.123403262,"remaining_time":2.210072783},
{"learn":[0.6775492145],"iteration":245,"passed_time":2.128842619,"remaining_time":2.198073273},
{"learn":[0.6774902801],"iteration":246,"passed_time":2.135714475,"remaining_time":2.187594179},
{"learn":[0.6774474788],"iteration":247,"passed_time":2.141263131,"remaining_time":2.175799633},
{"learn":[0.6774062915],"iteration":248,"passed_time":2.147064851,"remaining_time":2.164310352},
{"learn":[0.6774022265],"iteration":249,"passed_time":2.152476377,"remaining_time":2.152476377},
{"learn":[0.6773553954],"iteration":250,"passed_time":2.159421821,"remaining_time":2.142215272},
{"learn":[0.6773094456],"iteration":251,"passed_time":2.165728619,"remaining_time":2.131351975},
{"learn":[0.6772792856],"iteration":252,"passed_time":2.170630608,"remaining_time":2.119153203},
{"learn":[0.6772715454],"iteration":253,"passed_time":2.174819255,"remaining_time":2.106321011},
{"learn":[0.6772297918],"iteration":254,"passed_time":2.180573324,"remaining_time":2.095060644},
{"learn":[0.6771996945],"iteration":255,"passed_time":2.185870205,"remaining_time":2.083407539},
{"learn":[0.677165423],"iteration":256,"passed_time":2.191137497,"remaining_time":2.071775922},
{"learn":[0.6771236075],"iteration":257,"passed_time":2.196624275,"remaining_time":2.060399513},
{"learn":[0.6770980367],"iteration":258,"passed_time":2.202148299,"remaining_time":2.049103244},
{"learn":[0.6770369379],"iteration":259,"passed_time":2.207358968,"remaining_time":2.037562124},
{"learn":[0.6769930432],"iteration":260,"passed_time":2.212710332,"remaining_time":2.02619835},
{"learn":[0.6769631727],"iteration":261,"passed_time":2.219494817,"remaining_time":2.016182315},
{"learn":[0.6769504232],"iteration":262,"passed_time":2.224171129,"remaining_time":2.004291094},
{"learn":[0.6769215992],"iteration":263,"passed_time":2.230288404,"remaining_time":1.993742664},
{"learn":[0.6768572933],"iteration":264,"passed_time":2.235697601,"remaining_time":1.98259976},
{"learn":[0.6768252786],"iteration":265,"passed_time":2.241100673,"remaining_time":1.971494577},
{"learn":[0.6767971504],"iteration":266,"passed_time":2.247647633,"remaining_time":1.961430331},
{"learn":[0.6767731157],"iteration":267,"passed_time":2.253073882,"remaining_time":1.950422167},
{"learn":[0.6767532323],"iteration":268,"passed_time":2.258508145,"remaining_time":1.939462385},
{"learn":[0.6767199307],"iteration":269,"passed_time":2.264609679,"remaining_time":1.929111949},
{"learn":[0.6766750245],"iteration":270,"passed_time":2.272117998,"remaining_time":1.919981629},
{"learn":[0.6766470412],"iteration":271,"passed_time":2.277936229,"remaining_time":1.909446544},
{"learn":[0.6766069687],"iteration":272,"passed_time":2.286549567,"remaining_time":1.901270153},
{"learn":[0.67657834],"iteration":273,"passed_time":2.291800006,"remaining_time":1.890316793},
{"learn":[0.6765456272],"iteration":274,"passed_time":2.299384824,"remaining_time":1.881314856},
{"learn":[0.6765450664],"iteration":275,"passed_time":2.305770748,"remaining_time":1.871350172},
{"learn":[0.6765301947],"iteration":276,"passed_time":2.311793968,"remaining_time":1.861119332},
{"learn":[0.676489164],"iteration":277,"passed_time":2.31989848,"remaining_time":1.852580801},
{"learn":[0.6764553745],"iteration":278,"passed_time":2.325291209,"remaining_time":1.841897338},
{"learn":[0.6764168],"iteration":279,"passed_time":2.332604152,"remaining_time":1.832760405},
{"learn":[0.6763834829],"iteration":280,"passed_time":2.340377366,"remaining_time":1.823995171},
{"learn":[0.6763556783],"iteration":281,"passed_time":2.346745377,"remaining_time":1.814150681},
{"learn":[0.6763227589],"iteration":282,"passed_time":2.352753258,"remaining_time":1.804054618},
{"learn":[0.6762680117],"iteration":283,"passed_time":2.358308103,"remaining_time":1.793642783},
{"learn":[0.6762264296],"iteration":284,"passed_time":2.364847015,"remaining_time":1.784007397},
{"learn":[0.6762202303],"iteration":285,"passed_time":2.368816513,"remaining_time":1.772471097},
{"learn":[0.6762145588],"iteration":286,"passed_time":2.372489329,"remaining_time":1.760767342},
{"learn":[0.6761861566],"iteration":287,"passed_time":2.378591712,"remaining_time":1.750907788},
{"learn":[0.6761424837],"iteration":288,"passed_time":2.383851109,"remaining_time":1.740458768},
{"learn":[0.6761383555],"iteration":289,"passed_time":2.387813525,"remaining_time":1.729106346},
{"learn":[0.676105371],"iteration":290,"passed_time":2.395729722,"remaining_time":1.720644371},
{"learn":[0.6760753578],"iteration":291,"passed_time":2.401005159,"remaining_time":1.710305045},
{"learn":[0.6760417845],"iteration":292,"passed_time":2.40622583,"remaining_time":1.699961593},
{"learn":[0.6760109343],"iteration":293,"passed_time":2.413165531,"remaining_time":1.690857481},
{"learn":[0.6759919413],"iteration":294,"passed_time":2.418373491,"remaining_time":1.680564629},
{"learn":[0.6759571139],"iteration":295,"passed_time":2.42381765,"remaining_time":1.670468921},
{"learn":[0.6759178405],"iteration":296,"passed_time":2.430712765,"remaining_time":1.661396267},
{"learn":[0.6758750769],"iteration":297,"passed_time":2.43628518,"remaining_time":1.651441632},
{"learn":[0.6758441759],"iteration":298,"passed_time":2.442192669,"remaining_time":1.64174156},
{"learn":[0.6758019337],"iteration":299,"passed_time":2.447752419,"remaining_time":1.631834946},
{"learn":[0.6757702818],"iteration":300,"passed_time":2.452962213,"remaining_time":1.621725848},
{"learn":[0.6757260985],"iteration":301,"passed_time":2.458812995,"remaining_time":1.612069447},
{"learn":[0.6757184524],"iteration":302,"passed_time":2.464356028,"remaining_time":1.602238077},
{"learn":[0.6756721517],"iteration":303,"passed_time":2.469741053,"remaining_time":1.592333047},
{"learn":[0.6756417199],"iteration":304,"passed_time":2.475460455,"remaining_time":1.582671438},
{"learn":[0.6755854066],"iteration":305,"passed_time":2.480918441,"remaining_time":1.572869861},
{"learn":[0.6755239328],"iteration":306,"passed_time":2.486428506,"remaining_time":1.563129321},
{"learn":[0.6755065952],"iteration":307,"passed_time":2.492796,"remaining_time":1.553950753},
{"learn":[0.6754791342],"iteration":308,"passed_time":2.498294475,"remaining_time":1.544253219},
{"learn":[0.67543613],"iteration":309,"passed_time":2.503646554,"remaining_time":1.534493049},
{"learn":[0.6754045797],"iteration":310,"passed_time":2.509533854,"remaining_time":1.52508649},
{"learn":[0.6753792886],"iteration":311,"passed_time":2.51500177,"remaining_time":1.515449784},
{"learn":[0.6753462105],"iteration":312,"passed_time":2.52046291,"remaining_time":1.505835668},
{"learn":[0.6753124737],"iteration":313,"passed_time":2.526840598,"remaining_time":1.496790927},
{"learn":[0.6752849688],"iteration":314,"passed_time":2.532173612,"remaining_time":1.487149582},
{"learn":[0.6752555504],"iteration":315,"passed_time":2.537686112,"remaining_time":1.477640014},
{"learn":[0.6752092824],"iteration":316,"passed_time":2.543737151,"remaining_time":1.468466557},
{"learn":[0.6751870662],"iteration":317,"passed_time":2.549059917,"remaining_time":1.458895927},
{"learn":[0.6751676686],"iteration":318,"passed_time":2.554491092,"remaining_time":1.449413441},
{"learn":[0.6751533914],"iteration":319,"passed_time":2.559708165,"remaining_time":1.439835843},
{"learn":[0.6751490292],"iteration":320,"passed_time":2.563533066,"remaining_time":1.429509093},
{"learn":[0.6751067353],"iteration":321,"passed_time":2.568965501,"remaining_time":1.420111364},
{"learn":[0.675063311],"iteration":322,"passed_time":2.575488433,"remaining_time":1.411335767},
{"learn":[0.6750064278],"iteration":323,"passed_time":2.580662786,"remaining_time":1.401841513},
{"learn":[0.6749686208],"iteration":324,"passed_time":2.58657555,"remaining_time":1.39277145},
{"learn":[0.6749305566],"iteration":325,"passed_time":2.592615458,"remaining_time":1.383788618},
{"learn":[0.6749139944],"iteration":326,"passed_time":2.598016566,"remaining_time":1.374485828},
{"learn":[0.6748833227],"iteration":327,"passed_time":2.603192673,"remaining_time":1.365088841},
{"learn":[0.6748593929],"iteration":328,"passed_time":2.609780016,"remaining_time":1.356451011},
{"learn":[0.6748319972],"iteration":329,"passed_time":2.614845109,"remaining_time":1.34704142},
{"learn":[0.6747857528],"iteration":330,"passed_time":2.619967723,"remaining_time":1.337687448},
{"learn":[0.6747562576],"iteration":331,"passed_time":2.626119043,"remaining_time":1.328879516},
{"learn":[0.6747340665],"iteration":332,"passed_time":2.631488675,"remaining_time":1.319695521},
{"learn":[0.6746961284],"iteration":333,"passed_time":2.636610444,"remaining_time":1.310411179},
{"learn":[0.6746587343],"iteration":334,"passed_time":2.644584508,"remaining_time":1.302556549},
{"learn":[0.6746388756],"iteration":335,"passed_time":2.651005176,"remaining_time":1.293943003},
{"learn":[0.6746067004],"iteration":336,"passed_time":2.657049278,"remaining_time":1.285160334},
{"learn":[0.6745723985],"iteration":337,"passed_time":2.662421278,"remaining_time":1.276071737},
{"learn":[0.6745454632],"iteration":338,"passed_time":2.667855997,"remaining_time":1.267034854},
{"learn":[0.6745231505],"iteration":339,"passed_time":2.673998524,"remaining_time":1.258352247},
{"learn":[0.6745069656],"iteration":340,"passed_time":2.679458835,"remaining_time":1.249366436},
{"learn":[0.6744468436],"iteration":341,"passed_time":2.684800015,"remaining_time":1.240346206},
{"learn":[0.6744172648],"iteration":342,"passed_time":2.691057851,"remaining_time":1.231767005},
{"learn":[0.6743882888],"iteration":343,"passed_time":2.696615055,"remaining_time":1.222883572},
{"learn":[0.6743523799],"iteration":344,"passed_time":2.702050052,"remaining_time":1.213964516},
{"learn":[0.6743124243],"iteration":345,"passed_time":2.708351985,"remaining_time":1.205451461},
{"learn":[0.6742767883],"iteration":346,"passed_time":2.713957968,"remaining_time":1.196644291},
{"learn":[0.6742151633],"iteration":347,"passed_time":2.71958548,"remaining_time":1.187864922},
{"learn":[0.6741890595],"iteration":348,"passed_time":2.725437568,"remaining_time":1.179200782},
{"learn":[0.674182058],"iteration":349,"passed_time":2.730233831,"remaining_time":1.170100213},
{"learn":[0.6741348587],"iteration":350,"passed_time":2.735762706,"remaining_time":1.161335166},
{"learn":[0.6741135996],"iteration":351,"passed_time":2.742975654,"remaining_time":1.153296582},
{"learn":[0.6740901558],"iteration":352,"passed_time":2.748605724,"remaining_time":1.144603517},
{"learn":[0.6740537851],"iteration":353,"passed_time":2.754518904,"remaining_time":1.13604452},
{"learn":[0.6740283514],"iteration":354,"passed_time":2.759894456,"remaining_time":1.127280834},
{"learn":[0.6739976857],"iteration":355,"passed_time":2.76550878,"remaining_time":1.118632765},
{"learn":[0.6739719454],"iteration":356,"passed_time":2.77238595,"remaining_time":1.110507537},
{"learn":[0.6739305694],"iteration":357,"passed_time":2.778320942,"remaining_time":1.102015569},
{"learn":[0.67389042],"iteration":358,"passed_time":2.783728976,"remaining_time":1.093330879},
{"learn":[0.6738504358],"iteration":359,"passed_time":2.789826429,"remaining_time":1.0849325},
{"learn":[0.6738303355],"iteration":360,"passed_time":2.795261942,"remaining_time":1.076291994},
{"learn":[0.6737891685],"iteration":361,"passed_time":2.800886539,"remaining_time":1.067741277},
{"learn":[0.6737701031],"iteration":362,"passed_time":2.807127486,"remaining_time":1.059439299},
{"learn":[0.673744685],"iteration":363,"passed_time":2.812778195,"remaining_time":1.050928117},
{"learn":[0.6737161841],"iteration":364,"passed_time":2.818256824,"remaining_time":1.042368962},
{"learn":[0.6736840067],"iteration":365,"passed_time":2.825229868,"remaining_time":1.034373777},
{"learn":[0.6736841909],"iteration":366,"passed_time":2.828492204,"remaining_time":1.025039409},
{"learn":[0.6736526777],"iteration":367,"passed_time":2.834044751,"remaining_time":1.01655953},
{"learn":[0.6736151258],"iteration":368,"passed_time":2.840091086,"remaining_time":1.008270819},
{"learn":[0.6735460078],"iteration":369,"passed_time":2.84909181,"remaining_time":1.001032257},
{"learn":[0.6735067198],"iteration":370,"passed_time":2.858114757,"remaining_time":0.9937919234},
{"learn":[0.673481516],"iteration":371,"passed_time":2.865138978,"remaining_time":0.985854272},
{"learn":[0.6734508333],"iteration":372,"passed_time":2.876584745,"remaining_time":0.9794269774},
{"learn":[0.6734217036],"iteration":373,"passed_time":2.882548955,"remaining_time":0.9711261186},
{"learn":[0.673391989],"iteration":374,"passed_time":2.889341883,"remaining_time":0.9631139609},
{"learn":[0.6733682717],"iteration":375,"passed_time":2.894855699,"remaining_time":0.9546864538},
{"learn":[0.6733672588],"iteration":376,"passed_time":2.898072793,"remaining_time":0.9455250756},
{"learn":[0.6733236349],"iteration":377,"passed_time":2.904092404,"remaining_time":0.9372996649},
{"learn":[0.6732860186],"iteration":378,"passed_time":2.909360829,"remaining_time":0.9288460693},
{"learn":[0.6732662648],"iteration":379,"passed_time":2.91454044,"remaining_time":0.9203811917},
{"learn":[0.6732395353],"iteration":380,"passed_time":2.921002127,"remaining_time":0.9123339976},
{"learn":[0.6732350422],"iteration":381,"passed_time":2.924590471,"remaining_time":0.9034075276},
{"learn":[0.6732046259],"iteration":382,"passed_time":2.930017264,"remaining_time":0.8950705481},
{"learn":[0.6731640966],"iteration":383,"passed_time":2.936704406,"remaining_time":0.8871294559},
{"learn":[0.6731494355],"iteration":384,"passed_time":2.941303086,"remaining_time":0.8785710516},
{"learn":[0.6731253294],"iteration":385,"passed_time":2.946746909,"remaining_time":0.8702827658},
{"learn":[0.6730916826],"iteration":386,"passed_time":2.952627549,"remaining_time":0.8621367263},
{"learn":[0.6730595048],"iteration":387,"passed_time":2.95802699,"remaining_time":0.853863461},
{"learn":[0.6730369475],"iteration":388,"passed_time":2.963469884,"remaining_time":0.8456173705},
{"learn":[0.6730194756],"iteration":389,"passed_time":2.969529206,"remaining_time":0.8375595195},
{"learn":[0.6729848175],"iteration":390,"passed_time":2.974961607,"remaining_time":0.8293371231},
{"learn":[0.6729602617],"iteration":391,"passed_time":2.980314294,"remaining_time":0.8211069993},
{"learn":[0.6729409606],"iteration":392,"passed_time":2.986423675,"remaining_time":0.8130975401},
{"learn":[0.6729146442],"iteration":393,"passed_time":2.991722818,"remaining_time":0.804879743},
{"learn":[0.6728942994],"iteration":394,"passed_time":2.997231133,"remaining_time":0.7967323264},
{"learn":[0.6728467775],"iteration":395,"passed_time":3.003435582,"remaining_time":0.7887810618},
{"learn":[0.6728151505],"iteration":396,"passed_time":3.009054966,"remaining_time":0.7806868047},
{"learn":[0.6727968525],"iteration":397,"passed_time":3.014704985,"remaining_time":0.7726128352},
{"learn":[0.6727601354],"iteration":398,"passed_time":3.020925273,"remaining_time":0.7646953698},
{"learn":[0.6727369998],"iteration":399,"passed_time":3.026242928,"remaining_time":0.7565607321},
{"learn":[0.6727161946],"iteration":400,"passed_time":3.032016877,"remaining_time":0.7485527951},
{"learn":[0.6726879885],"iteration":401,"passed_time":3.03759555,"remaining_time":0.740508368},
{"learn":[0.6726517636],"iteration":402,"passed_time":3.043285698,"remaining_time":0.7325030092},
{"learn":[0.6726155916],"iteration":403,"passed_time":3.049324698,"remaining_time":0.7245920075},
{"learn":[0.6725850106],"iteration":404,"passed_time":3.054698734,"remaining_time":0.7165342708},
{"learn":[0.6725767861],"iteration":405,"passed_time":3.059664438,"remaining_time":0.7083952147},
{"learn":[0.6725500336],"iteration":406,"passed_time":3.0659244,"remaining_time":0.7005674919},
{"learn":[0.6725274725],"iteration":407,"passed_time":3.071276155,"remaining_time":0.6925426625},
{"learn":[0.6724943676],"iteration":408,"passed_time":3.076662046,"remaining_time":0.6845384992},
{"learn":[0.6724631577],"iteration":409,"passed_time":3.082798113,"remaining_time":0.6767117809},
{"learn":[0.6724223491],"iteration":410,"passed_time":3.088304155,"remaining_time":0.6687568608},
{"learn":[0.6723800552],"iteration":411,"passed_time":3.093873841,"remaining_time":0.6608274223},
{"learn":[0.6723312064],"iteration":412,"passed_time":3.100049381,"remaining_time":0.6530370366},
{"learn":[0.672299212],"iteration":413,"passed_time":3.105430745,"remaining_time":0.6450894784},
{"learn":[0.672284233],"iteration":414,"passed_time":3.110679961,"remaining_time":0.637127221},
{"learn":[0.6722750903],"iteration":415,"passed_time":3.116013748,"remaining_time":0.6291950838},
{"learn":[0.6722449519],"iteration":416,"passed_time":3.121504428,"remaining_time":0.6213066367},
{"learn":[0.6722173721],"iteration":417,"passed_time":3.126973894,"remaining_time":0.6134255008},
{"learn":[0.6721924643],"iteration":418,"passed_time":3.135049791,"remaining_time":0.6060597448},
{"learn":[0.6721684246],"iteration":419,"passed_time":3.141999971,"remaining_time":0.598476185},
{"learn":[0.6721377229],"iteration":420,"passed_time":3.147994199,"remaining_time":0.5907162512},
{"learn":[0.6720982037],"iteration":421,"passed_time":3.153373212,"remaining_time":0.5828509729},
{"learn":[0.672067977],"iteration":422,"passed_time":3.158731612,"remaining_time":0.5749936977},
{"learn":[0.6720625364],"iteration":423,"passed_time":3.164252073,"remaining_time":0.5671772583},
{"learn":[0.6720393431],"iteration":424,"passed_time":3.169384042,"remaining_time":0.5593030662},
{"learn":[0.6720081086],"iteration":425,"passed_time":3.1749361,"remaining_time":0.5515147216},
{"learn":[0.6719502848],"iteration":426,"passed_time":3.181194249,"remaining_time":0.5438575649},
{"learn":[0.6719295335],"iteration":427,"passed_time":3.186264466,"remaining_time":0.5360071064},
{"learn":[0.6718877607],"iteration":428,"passed_time":3.191791929,"remaining_time":0.5282452844},
{"learn":[0.6718611302],"iteration":429,"passed_time":3.19768673,"remaining_time":0.5205536537},
{"learn":[0.6718301288],"iteration":430,"passed_time":3.203104492,"remaining_time":0.5127939907},
{"learn":[0.6718008906],"iteration":431,"passed_time":3.208414979,"remaining_time":0.5050282837},
{"learn":[0.6717733045],"iteration":432,"passed_time":3.214516062,"remaining_time":0.4973962497},
{"learn":[0.6717539089],"iteration":433,"passed_time":3.219579554,"remaining_time":0.4896134805},
{"learn":[0.671732319],"iteration":434,"passed_time":3.22517782,"remaining_time":0.4819231226},
{"learn":[0.6717256004],"iteration":435,"passed_time":3.229976978,"remaining_time":0.474125061},
{"learn":[0.6716999521],"iteration":436,"passed_time":3.235429771,"remaining_time":0.4664349556},
{"learn":[0.6716961006],"iteration":437,"passed_time":3.239708889,"remaining_time":0.4585889295},
{"learn":[0.6716727744],"iteration":438,"passed_time":3.245352694,"remaining_time":0.4509487798},
{"learn":[0.6716512168],"iteration":439,"passed_time":3.251042629,"remaining_time":0.4433239949},
{"learn":[0.6716255468],"iteration":440,"passed_time":3.25614188,"remaining_time":0.435628959},
{"learn":[0.6716010265],"iteration":441,"passed_time":3.26291515,"remaining_time":0.4281653364},
{"learn":[0.6715685398],"iteration":442,"passed_time":3.268231108,"remaining_time":0.4205173209},
{"learn":[0.6715485374],"iteration":443,"passed_time":3.273633027,"remaining_time":0.4128906521},
{"learn":[0.6715125934],"iteration":444,"passed_time":3.281787314,"remaining_time":0.4056141624},
{"learn":[0.6714978688],"iteration":445,"passed_time":3.287005227,"remaining_time":0.3979782113},
{"learn":[0.6714710486],"iteration":446,"passed_time":3.29251632,"remaining_time":0.3903878411},
{"learn":[0.6714473413],"iteration":447,"passed_time":3.298865506,"remaining_time":0.3829040319},
{"learn":[0.6714291075],"iteration":448,"passed_time":3.304411002,"remaining_time":0.3753339891},
{"learn":[0.6713954211],"iteration":449,"passed_time":3.310264701,"remaining_time":0.3678071889},
{"learn":[0.6713739838],"iteration":450,"passed_time":3.315750221,"remaining_time":0.3602478067},
{"learn":[0.6713468236],"iteration":451,"passed_time":3.321140532,"remaining_time":0.3526874901},
{"learn":[0.6713281729],"iteration":452,"passed_time":3.327560944,"remaining_time":0.34524363},
{"learn":[0.6713022288],"iteration":453,"passed_time":3.332873327,"remaining_time":0.3376920111},
{"learn":[0.6712684459],"iteration":454,"passed_time":3.338169041,"remaining_time":0.3301485865},
{"learn":[0.6712393939],"iteration":455,"passed_time":3.344420703,"remaining_time":0.3227072608},
{"learn":[0.671213972],"iteration":456,"passed_time":3.349652021,"remaining_time":0.3151751354},
{"learn":[0.671184047],"iteration":457,"passed_time":3.355065211,"remaining_time":0.3076697355},
{"learn":[0.6711363525],"iteration":458,"passed_time":3.361153031,"remaining_time":0.300233713},
{"learn":[0.6711043221],"iteration":459,"passed_time":3.366381636,"remaining_time":0.2927288379},
{"learn":[0.6710759518],"iteration":460,"passed_time":3.372930643,"remaining_time":0.2853455424},
{"learn":[0.6710404956],"iteration":461,"passed_time":3.379242011,"remaining_time":0.2779463126},
{"learn":[0.6709952081],"iteration":462,"passed_time":3.384575165,"remaining_time":0.2704736093},
{"learn":[0.6709736702],"iteration":463,"passed_time":3.39009753,"remaining_time":0.2630248083},
{"learn":[0.6709605449],"iteration":464,"passed_time":3.3977186,"remaining_time":0.2557422602},
{"learn":[0.670923932],"iteration":465,"passed_time":3.40316958,"remaining_time":0.2482999264},
{"learn":[0.6709005251],"iteration":466,"passed_time":3.410399232,"remaining_time":0.2409918087},
{"learn":[0.6708643519],"iteration":467,"passed_time":3.416368106,"remaining_time":0.2335978192},
{"learn":[0.6708291365],"iteration":468,"passed_time":3.421903049,"remaining_time":0.226181225},
{"learn":[0.6708103459],"iteration":469,"passed_time":3.429648358,"remaining_time":0.218913725},
{"learn":[0.6707941451],"iteration":470,"passed_time":3.434900496,"remaining_time":0.2114906887},
{"learn":[0.6707627109],"iteration":471,"passed_time":3.440785228,"remaining_time":0.204114378},
{"learn":[0.6707421102],"iteration":472,"passed_time":3.445847466,"remaining_time":0.1966974241},
{"learn":[0.670724667],"iteration":473,"passed_time":3.450865162,"remaining_time":0.1892879625},
{"learn":[0.6707028318],"iteration":474,"passed_time":3.456444838,"remaining_time":0.1819181494},
{"learn":[0.6706839397],"iteration":475,"passed_time":3.461731472,"remaining_time":0.1745410826},
{"learn":[0.670663005],"iteration":476,"passed_time":3.467213343,"remaining_time":0.1671821947},
{"learn":[0.6706539707],"iteration":477,"passed_time":3.471969596,"remaining_time":0.1597977638},
{"learn":[0.6706351543],"iteration":478,"passed_time":3.478225916,"remaining_time":0.1524900715},
{"learn":[0.6706079427],"iteration":479,"passed_time":3.48361512,"remaining_time":0.14515063},
{"learn":[0.670569047],"iteration":480,"passed_time":3.489486603,"remaining_time":0.1378383481},
{"learn":[0.6705457203],"iteration":481,"passed_time":3.495088569,"remaining_time":0.1305219798},
{"learn":[0.670521002],"iteration":482,"passed_time":3.500511182,"remaining_time":0.1232063977},
{"learn":[0.6705014213],"iteration":483,"passed_time":3.506173353,"remaining_time":0.1159065571},
{"learn":[0.6704784071],"iteration":484,"passed_time":3.511545963,"remaining_time":0.1086045143},
{"learn":[0.6704354399],"iteration":485,"passed_time":3.517120937,"remaining_time":0.101316241},
{"learn":[0.6704170188],"iteration":486,"passed_time":3.522730903,"remaining_time":0.09403593787},
{"learn":[0.6703826063],"iteration":487,"passed_time":3.528010318,"remaining_time":0.08675435208},
{"learn":[0.6703501485],"iteration":488,"passed_time":3.533012711,"remaining_time":0.07947472356},
{"learn":[0.6703247936],"iteration":489,"passed_time":3.538680636,"remaining_time":0.07221797217},
{"learn":[0.6703062309],"iteration":490,"passed_time":3.544217058,"remaining_time":0.06496528212},
{"learn":[0.6702857115],"iteration":491,"passed_time":3.549668179,"remaining_time":0.05771818177},
{"learn":[0.670254477],"iteration":492,"passed_time":3.555822722,"remaining_time":0.05048835508},
{"learn":[0.6702327907],"iteration":493,"passed_time":3.561697258,"remaining_time":0.04325948087},
{"learn":[0.6702018208],"iteration":494,"passed_time":3.567796078,"remaining_time":0.03603834422},
{"learn":[0.6701810786],"iteration":495,"passed_time":3.573650485,"remaining_time":0.02881976197},
{"learn":[0.6701493884],"iteration":496,"passed_time":3.578850423,"remaining_time":0.02160271885},
{"learn":[0.6701109439],"iteration":497,"passed_time":3.584259191,"remaining_time":0.01439461523},
{"learn":[0.6700651585],"iteration":498,"passed_time":3.589786745,"remaining_time":0.007193961414},
{"learn":[0.6700388862],"iteration":499,"passed_time":3.595077274,"remaining_time":0}
]}